wordstats/__init__.py
wordstats/base_service.py
wordstats/common_words.py
wordstats/config.py
wordstats/data_downloader.py
wordstats/language_codes.py
wordstats/language_info.py
wordstats/loading_from_hermit.py
wordstats/metrics_computers.py
wordstats/word_info.py
wordstats/word_stats.py
wordstats/language_data/common/common.txt
wordstats/language_data/hermitdave/LICENSE
wordstats/language_data/hermitdave/2018/da/da_full.txt
wordstats/language_data/hermitdave/2018/de/de_full.txt
wordstats/language_data/hermitdave/2018/el/el_full.txt
wordstats/language_data/hermitdave/2018/en/en_full.txt
wordstats/language_data/hermitdave/2018/es/es_full.txt
wordstats/language_data/hermitdave/2018/fr/fr_full.txt
wordstats/language_data/hermitdave/2018/hu/hu_full.txt
wordstats/language_data/hermitdave/2018/it/it_full.txt
wordstats/language_data/hermitdave/2018/nl/nl_full.txt
wordstats/language_data/hermitdave/2018/no/no_full.txt
wordstats/language_data/hermitdave/2018/pl/pl_full.txt
wordstats/language_data/hermitdave/2018/pt/pt_full.txt
wordstats/language_data/hermitdave/2018/ro/ro_full.txt
wordstats/language_data/hermitdave/2018/ru/ru_full.txt
wordstats/language_data/hermitdave/2018/sv/sv_full.txt
wordstats/tests/__init__.py
wordstats/tests/test_basics.py
wordstats/tests/test_performance.py
wordstats/tests/tests.py
wordstats/utils/__init__.py
wordstats/utils/mem_footprint.py
wordstats-1.1.0.dist-info/licenses/LICENSE
wordstats-1.1.0.dist-info/METADATA
wordstats-1.1.0.dist-info/WHEEL
wordstats-1.1.0.dist-info/top_level.txt
wordstats-1.1.0.dist-info/RECORD
