Metadata-Version: 2.4
Name: wordstats
Version: 1.1.0
Summary: Multilingual word frequency statistics for Python based on subtitles corpora
Home-page: https://github.com/zeeguu-ecosystem/Python-Wordstats
Download-URL: https://github.com/zeeguu-ecosystem/Python-Wordstats/archive/v_1.0.7.tar.gz
Author: Mircea Lungu
Author-email: mircea.lungu@gmail.com
License: MIT
Keywords: natural language processing,multilingual
Classifier: Development Status :: 4 - Beta
Classifier: Intended Audience :: Developers
Classifier: Topic :: Text Processing :: Linguistic
Classifier: License :: OSI Approved :: MIT License
Classifier: Programming Language :: Python :: 3
Classifier: Programming Language :: Python :: 3.4
Classifier: Programming Language :: Python :: 3.5
Classifier: Programming Language :: Python :: 3.6
License-File: LICENSE
Requires-Dist: configobj
Requires-Dist: sqlalchemy
Dynamic: author
Dynamic: author-email
Dynamic: classifier
Dynamic: description
Dynamic: description-content-type
Dynamic: download-url
Dynamic: home-page
Dynamic: keywords
Dynamic: license
Dynamic: license-file
Dynamic: requires-dist
Dynamic: summary
